{"uuid": "70893d41-e875-68c3-91b7-5e18347b0552", "state": {"code": "confirmed", "et": "Kinnitatud", "en": "confirmed"}, "last_update": "2025-02-04T14:12:17", "title": {"en": "Anaesthesiology and Intensive Care", "et": "Anestesioloogia ja intensiivravi"}, "credits": 3, "credit_type": "ECTS", "target": {"year": {"code": "2024", "et": "2024/2025", "en": "2024/2025"}, "semester": {"code": "spring", "et": "kevad", "en": "spring"}, "study_type": {"code": "fulltime", "et": "päevaõpe", "en": "regular studies"}, "language": {"code": "et", "et": "eesti keel", "en": "Estonian"}, "part": {"code": "0", "et": "Osadeta", "en": "None"}, "faculty": {"code": "MV", "name": {"en": "Faculty of Medicine", "et": "meditsiiniteaduste valdkond"}, "address": "Tartu linn, \nTartu linn, Tartumaa \nEST", "city": "Tartu linn", "level": 1, "academic": true, "supports_continuous_learning": true}, "course_main_structural_unit": {"code": "MVCM01", "name": {"en": "Department of Anesthesiology and Intensive Care", "et": "anestesioloogia ja intensiivravi kliinik"}, "phone": "+372 731 8405", "webpage_url": "https://kliinilinemeditsiin.ut.ee/et/anestesioloogia-intensiivravi-kliinik", "address": "L. Puusepa 8 - G1. 209\n50406 Tartu linn, \nTartu linn, Tartumaa \nEST", "city": "Tartu linn", "street": "L. Puusepa 8 - G1. 209", "zip": "50406", "level": 3, "academic": true, "supports_continuous_learning": false, "parent_code": "MVCM"}, "label": {"en": "24/25 S regular MV", "et": "24/25 K PÕ MV"}}, "general": {"year": {"code": "2024", "et": "2024/2025", "en": "2024/2025"}, "input_languages": [{"code": "et", "et": "eesti keel", "en": "Estonian"}], "structural_unit_shares": [{"structural_unit_code": "MVCM01", "structural_unit_name": {"en": "Department of Anesthesiology and Intensive Care", "et": "anestesioloogia ja intensiivravi kliinik"}, "course_share_percent": 100, "coordinating": true}], "type": {"code": "regular", "et": "Tavaline aine", "en": "Regular course"}}, "additional_info": {"is_vota_course": true, "is_continuous_learning_course": false, "study_levels": [{"code": "bachelor", "et": "bakalaureuseõpe", "en": "bachelor's studies"}], "hours": {"lecture": 14, "practice": 24, "seminar": 0, "colloquium": 0, "web_learning": 0, "independent_work": 40, "individual_work": 0, "internship": 0}, "prerequisites": [{"required": false, "uuid": "0c287aaa-1022-3da7-795d-7e0e7f518acd", "code": "ARPA.01.023", "title": {"en": "Pathological Anatomy", "et": "Patoloogiline anatoomia"}, "credits": 3, "state": {"code": "confirmed", "et": "Kinnitatud", "en": "confirmed"}, "last_update": "2024-02-05T11:04:36"}], "is_enlight_course": false}, "overview": {"study_languages": [{"code": "et", "et": "eesti keel", "en": "Estonian"}], "description": {"en": "-", "et": "Kursus annab esmase ettevalmistuse abi osutamiseks eluohtlikus seisundis oleva kannatanule. Koolituse põhirõhk on elustamisvõtetel omandamisel ja treenimisel. Arvestusel näitab üliõpilane oma oskusi praktiliste situatsioonülesannete lahendamises, näiteks tegevus liiklusõnnetuses kannatanute abistamisel, praktilised elustamisvõtted südame äkksurma korral jne. Lisaks saavad kursuse läbinud üliõpilased ülevaate intensiivravi haige elutähtsate funktsioonide tagamisest ning jälgimisest. Kursusel tutvustatakse patsiendimonitoride, respiraatorite, jm. aparatuuei tööpõhimõtteid."}, "objectives": [{"en": "-", "et": "Anda füsioteraapia üliõpilastele vajalikud baasteadmised esmaabist ja intensiivravi haigega tegelemiseks."}], "learning_outcomes": [{"en": "-", "et": "Kursuse läbinud üliõpilane:\n- tunneb ära kriitilises seisundis kannatanu ja oskab anda talle esmaabi;\n- teab hingamispuudulikkuse tekkemehhanisme ning peamisi ravimeetodeid;\n- orienteerub intensiivravi keskkonnas, tunneb patsiendi monitori tööpõhimõtteid ja peamisi jälgitavaid parameetreid;\n- tunneb kaasaegse valuravi põhiprintsiipe."}], "notes": {"et": "Loengud on üleval MOODLEs. Vaadake neid enne praktikumide algust.\nPraktikumid toimuvad vastavalt tunniplaanile."}}, "grading": {"independent_work": {}, "independent_work_assessments": [{"work_type": {"code": "practical", "et": "Praktiline ülesanne", "en": "practical assignment"}, "description": {"et": "lävendihindamine (arvestatud/mittearvestatud)"}}], "grade_preconditions": {"et": "Osalemine kõikides praktikumides."}, "grade_evaluation": {}, "debt_elimination": {"et": "Kokkuleppel õppejõuga."}, "assessment_scale": {"code": "pass", "et": "Eristamata (arv, m.arv, mi)", "en": "non-differentiated (pass, fail, not present)"}, "results_available_from": {}}, "resources": {"web_based": {"code": "2", "et": "põimõpe", "en": "blended learning"}, "website_url": "https://moodle.ut.ee/course/view.php?id=983", "is_moodle_connected": true, "learning_environments": [{"uuid": "10d9d0f5-eda8-4c2d-be5b-f7e1e76f93f9", "type": "MOODLE", "code": "ARAI.01.043", "base_url": "undefined", "linked_to_groups": ["f2e47fb7-b5fa-c809-c0b5-a83dff5ac06a", "2b2605b8-1407-c917-ef12-ab66b098845c", "69d5a990-d7f0-5614-0775-32b753fe8d20"], "is_auto_update": false, "is_default": true, "is_auto_grading": false}]}, "participants": {"lecturers": [{"person_uuid": "556eea41-f190-c414-b0a6-e29e7d2b01db", "person_name": "Kadri Tamme", "structural_unit": {"code": "MVCM01", "name": {"en": "Department of Anesthesiology and Intensive Care", "et": "anestesioloogia ja intensiivravi kliinik"}, "phone": "+372 731 8405", "webpage_url": "https://kliinilinemeditsiin.ut.ee/et/anestesioloogia-intensiivravi-kliinik", "address": "L. Puusepa 8 - G1. 209\n50406 Tartu linn, \nTartu linn, Tartumaa \nEST", "city": "Tartu linn", "street": "L. Puusepa 8 - G1. 209", "zip": "50406", "level": 3, "academic": true, "supports_continuous_learning": false, "parent_code": "MVCM"}, "is_responsible": true, "is_teaching": true, "study_group_roles": {"2 rühm": {"code": "2", "et": "Praktikumijuhendaja", "en": "supervisor of practical class"}, "3. rühm": {"code": "2", "et": "Praktikumijuhendaja", "en": "supervisor of practical class"}, "1 rühm": {"code": "2", "et": "Praktikumijuhendaja", "en": "supervisor of practical class"}}}, {"person_uuid": "883e8c1d-63bd-f39d-0bd7-a36d1fc3aaaa", "person_name": "Aleksander Sipria", "structural_unit": {"code": "MVCM01", "name": {"en": "Department of Anesthesiology and Intensive Care", "et": "anestesioloogia ja intensiivravi kliinik"}, "phone": "+372 731 8405", "webpage_url": "https://kliinilinemeditsiin.ut.ee/et/anestesioloogia-intensiivravi-kliinik", "address": "L. Puusepa 8 - G1. 209\n50406 Tartu linn, \nTartu linn, Tartumaa \nEST", "city": "Tartu linn", "street": "L. Puusepa 8 - G1. 209", "zip": "50406", "level": 3, "academic": true, "supports_continuous_learning": false, "parent_code": "MVCM"}, "is_responsible": false, "is_teaching": true, "study_group_roles": {"2 rühm": {"code": "1", "et": "Lektor", "en": "lecturer"}, "3. rühm": {"code": "1", "et": "Lektor", "en": "lecturer"}, "1 rühm": {"code": "1", "et": "Lektor", "en": "lecturer"}}}, {"person_uuid": "2af5ed43-d9c0-7723-5b4b-978afe856082", "person_name": "Joel Starkopf", "structural_unit": {"code": "MVCM01", "name": {"en": "Department of Anesthesiology and Intensive Care", "et": "anestesioloogia ja intensiivravi kliinik"}, "phone": "+372 731 8405", "webpage_url": "https://kliinilinemeditsiin.ut.ee/et/anestesioloogia-intensiivravi-kliinik", "address": "L. Puusepa 8 - G1. 209\n50406 Tartu linn, \nTartu linn, Tartumaa \nEST", "city": "Tartu linn", "street": "L. Puusepa 8 - G1. 209", "zip": "50406", "level": 3, "academic": true, "supports_continuous_learning": false, "parent_code": "MVCM"}, "is_responsible": false, "is_teaching": true, "study_group_roles": {"2 rühm": {"code": "1", "et": "Lektor", "en": "lecturer"}, "3. rühm": {"code": "1", "et": "Lektor", "en": "lecturer"}, "1 rühm": {"code": "1", "et": "Lektor", "en": "lecturer"}}}, {"person_uuid": "5ae4893f-2d86-6700-c252-81924e5d3aa9", "person_name": "Aleksandr Beljantsev", "structural_unit": {"code": "MVCM01", "name": {"en": "Department of Anesthesiology and Intensive Care", "et": "anestesioloogia ja intensiivravi kliinik"}, "phone": "+372 731 8405", "webpage_url": "https://kliinilinemeditsiin.ut.ee/et/anestesioloogia-intensiivravi-kliinik", "address": "L. Puusepa 8 - G1. 209\n50406 Tartu linn, \nTartu linn, Tartumaa \nEST", "city": "Tartu linn", "street": "L. Puusepa 8 - G1. 209", "zip": "50406", "level": 3, "academic": true, "supports_continuous_learning": false, "parent_code": "MVCM"}, "is_responsible": false, "is_teaching": true, "study_group_roles": {"2 rühm": {"code": "2", "et": "Praktikumijuhendaja", "en": "supervisor of practical class"}, "3. rühm": {"code": "2", "et": "Praktikumijuhendaja", "en": "supervisor of practical class"}, "1 rühm": {"code": "2", "et": "Praktikumijuhendaja", "en": "supervisor of practical class"}}}, {"person_uuid": "7d8b9a39-5cb4-f1cf-56d5-751774dc398d", "person_name": "Olavi Maasikas", "structural_unit": {"code": "MVCM01", "name": {"en": "Department of Anesthesiology and Intensive Care", "et": "anestesioloogia ja intensiivravi kliinik"}, "phone": "+372 731 8405", "webpage_url": "https://kliinilinemeditsiin.ut.ee/et/anestesioloogia-intensiivravi-kliinik", "address": "L. Puusepa 8 - G1. 209\n50406 Tartu linn, \nTartu linn, Tartumaa \nEST", "city": "Tartu linn", "street": "L. Puusepa 8 - G1. 209", "zip": "50406", "level": 3, "academic": true, "supports_continuous_learning": false, "parent_code": "MVCM"}, "is_responsible": false, "is_teaching": true, "study_group_roles": {"2 rühm": {"code": "2", "et": "Praktikumijuhendaja", "en": "supervisor of practical class"}, "3. rühm": {"code": "2", "et": "Praktikumijuhendaja", "en": "supervisor of practical class"}, "1 rühm": {"code": "2", "et": "Praktikumijuhendaja", "en": "supervisor of practical class"}}}, {"person_uuid": "1477f81d-e88b-f6c0-225d-abbb98da82d8", "person_name": "Karri Kase", "structural_unit": {"code": "MV", "name": {"en": "Faculty of Medicine", "et": "meditsiiniteaduste valdkond"}, "address": "Tartu linn, \nTartu linn, Tartumaa \nEST", "city": "Tartu linn", "level": 1, "academic": true, "supports_continuous_learning": true}, "is_responsible": false, "is_teaching": true, "study_group_roles": {"2 rühm": {"code": "2", "et": "Praktikumijuhendaja", "en": "supervisor of practical class"}, "3. rühm": {"code": "2", "et": "Praktikumijuhendaja", "en": "supervisor of practical class"}, "1 rühm": {"code": "2", "et": "Praktikumijuhendaja", "en": "supervisor of practical class"}}}], "assistants": ["56e03adc-7459-5b31-8bc2-63564505e597"], "study_groups": [{"uuid": "f2e47fb7-b5fa-c809-c0b5-a83dff5ac06a", "code": "1 rühm", "max_size": 15}, {"uuid": "69d5a990-d7f0-5614-0775-32b753fe8d20", "code": "2 rühm", "max_size": 15}, {"uuid": "2b2605b8-1407-c917-ef12-ab66b098845c", "code": "3. rühm", "max_size": 15}]}, "schedule": {"weeks": {"et": "24-34"}, "entries": [{"work_type": {"code": "lecture", "et": "loeng", "en": "lecture"}, "topic": {}, "description": {"et": "Äkksurm. Taaselustamine kliinilisest surmast."}}, {"work_type": {"code": "lecture", "et": "loeng", "en": "lecture"}, "topic": {}, "description": {"et": "Palavik, süsteemne põletikureaktsioon ja sepsis."}}, {"work_type": {"code": "lecture", "et": "loeng", "en": "lecture"}, "topic": {}, "description": {"et": "Hapniku transport ja selle hindamine intensiivravi patsiendil. Šokk."}}, {"work_type": {"code": "lecture", "et": "loeng", "en": "lecture"}, "topic": {}, "description": {"et": "Intensiivravi ajalugu. Intensiivravi patsiendi lihasnõrkus."}}, {"work_type": {"code": "lecture", "et": "loeng", "en": "lecture"}, "topic": {}, "description": {"et": "Füsioteraapia intensiivravi patsientidel."}}, {"work_type": {"code": "lecture", "et": "loeng", "en": "lecture"}, "topic": {}, "description": {"et": "Teadvusehäired I - kooma."}}, {"work_type": {"code": "lecture", "et": "loeng", "en": "lecture"}, "topic": {}, "description": {"et": "Teadvushäired II - intensiivravi haige deliirium."}}, {"work_type": {"code": "practice", "et": "praktikum", "en": "practical session"}, "topic": {}, "description": {"et": "Taaselustamise ABC. Taaselustamine eriolukordades. Võõrkeha hingamisteedes. Uppumine."}}, {"work_type": {"code": "practice", "et": "praktikum", "en": "practical session"}, "topic": {}, "description": {"et": "Kirurgilised haavad, haavade paranemine. \nFüsioteraapia kirurgilisele haigele."}}, {"work_type": {"code": "practice", "et": "praktikum", "en": "practical session"}, "topic": {}, "description": {"et": "Intensiivravis kasutatav aparatuur - voodi, patsiendimonitor, hingamisaparaat. \nIntensiivravi haige jälgimine, põetus ja füsioteraapia."}}, {"work_type": {"code": "practice", "et": "praktikum", "en": "practical session"}, "topic": {}, "description": {"et": "Äge hingamispuudulikkus. Kunstlik hingamine. \nRespiratoorne füsioteraapia."}}, {"work_type": {"code": "practice", "et": "praktikum", "en": "practical session"}, "topic": {}, "description": {"et": "Teadvuseta haige jälgimine ja põetus. \nIntensiivravi haige lihasnõrkus."}}, {"work_type": {"code": "practice", "et": "praktikum", "en": "practical session"}, "topic": {}, "description": {"et": "Arvestus."}}]}, "registration_info": {"audience": {"et": "Füsioteraapia 2.kursus"}, "max_students": 45}, "parent_uuid": "c1ac45c7-4086-bc56-ac43-483d84069310", "parent_code": "ARAI.01.043", "parent_credits": 3, "_actions": {"is_moodle_editable": false, "is_editable": false, "is_deletable": false}}