{"uuid": "6c14040d-4d0d-bd53-192d-f7b36b0730db", "code": "HVVK.04.046", "state": {"code": "confirmed", "et": "Kinnitatud", "en": "confirmed"}, "last_update": "2024-02-05T11:04:36", "title": {"en": "The Master Classes of Acting Studies II", "et": "Näitlejatöö meistriklassid II"}, "credits": 5, "general": {"input_languages": [{"code": "et", "et": "eesti keel", "en": "Estonian"}], "structural_unit_shares": [{"structural_unit_code": "HVVK", "structural_unit_name": {"en": "Viljandi Culture Academy", "et": "Viljandi kultuuriakadeemia"}, "course_share_percent": 100, "coordinating": true}], "type": {"code": "regular", "et": "Tavaline aine", "en": "Regular course"}, "structural_units": [{"code": "HVVK", "name": {"en": "Viljandi Culture Academy", "et": "Viljandi kultuuriakadeemia"}, "email": "kultuur@ut.ee", "phone": "+372 435 5232", "webpage_url": "https://viljandi.ut.ee", "address": "Posti 1\n71004 Viljandi linn, \nViljandimaa \nEST", "city": "Viljandi linn", "street": "Posti 1", "zip": "71004", "level": 2, "academic": true, "supports_continuous_learning": true, "parent_code": "HV"}]}, "additional_info": {"duration_in_semesters": 2, "occurrence_frequency": {"code": "other_year", "et": "üle õppeaasta", "en": "every other academic year"}, "assessment_scale": {"code": "grade", "et": "Eristav (A, B, C, D, E, F, mi)", "en": "differentiated (A, B, C, D, E, F, not present)"}, "is_vota_course": true, "is_continuous_learning_course": false}, "overview": {"description": {"en": "The form and the content of the study is assigned by guest lecturer.", "et": "Õppetöö vormi ja sisu määrab meistriklassi läbi viiv külalisõppejõud."}, "objectives": [{"en": "Involving specialists and working practicioners to the studies.", "et": "Oma eriala spetsialistide ja tegevpraktikute kaasamine õppetöösse."}], "learning_outcomes": [{"en": "Student got an experience to work in a creative process with different specialists and working practicioners.", "et": "Üliõpilane on saanud kogemuse töötada loomingulises protsessis erinevate eriala spetsialistide ja tegevpraktikutega."}]}, "_actions": {"is_editable": false, "is_version_creatable": false, "is_deletable": false}}