{"uuid": "24264ec7-0f49-3745-0d10-12e0e99da27f", "code": "HVVK.02.056", "state": {"code": "confirmed", "et": "Kinnitatud", "en": "confirmed"}, "last_update": "2024-02-05T11:04:36", "title": {"en": "Main Instrument III", "et": "Erialainstrument III"}, "credits": 6, "general": {"input_languages": [{"code": "et", "et": "eesti keel", "en": "Estonian"}], "structural_unit_shares": [{"structural_unit_code": "HVVK", "structural_unit_name": {"en": "Viljandi Culture Academy", "et": "Viljandi kultuuriakadeemia"}, "course_share_percent": 100, "coordinating": true}], "type": {"code": "regular", "et": "Tavaline aine", "en": "Regular course"}, "structural_units": [{"code": "HVVK", "name": {"en": "Viljandi Culture Academy", "et": "Viljandi kultuuriakadeemia"}, "email": "kultuur@ut.ee", "phone": "+372 435 5232", "webpage_url": "https://viljandi.ut.ee", "address": "Posti 1\n71004 Viljandi linn, \nViljandimaa \nEST", "city": "Viljandi linn", "street": "Posti 1", "zip": "71004", "level": 2, "academic": true, "supports_continuous_learning": true, "parent_code": "HV"}]}, "additional_info": {"duration_in_semesters": 2, "assessment_scale": {"code": "grade", "et": "Eristav (A, B, C, D, E, F, mi)", "en": "differentiated (A, B, C, D, E, F, not present)"}, "is_vota_course": true, "is_continuous_learning_course": false, "prerequisites": [{"required": true, "uuid": "cf2e06ea-ea73-0d69-f603-2d8da4fad8a0", "code": "HVVK.02.055", "title": {"en": "Main Instrument II", "et": "Erialainstrument II"}, "credits": 9, "state": {"code": "confirmed", "et": "Kinnitatud", "en": "confirmed"}, "last_update": "2024-08-26T13:14:32"}, {"required": true, "uuid": "882af743-8e2d-7efc-9707-fcf888c1a38c", "code": "P2VK.02.647", "title": {"en": "Music Theory II", "et": "Muusikateooria II"}, "credits": 3, "state": {"code": "confirmed", "et": "Kinnitatud", "en": "confirmed"}, "last_update": "2024-02-05T11:04:36"}]}, "overview": {"description": {"en": "Developing the transcribing and improvising skills, study of jazz repertoire.", "et": "Transkribeerimis- ja improviseerimisoskuste arendamine, jazzrepertuaari omandamine."}, "objectives": [{"en": "Developing the proficiency on one's main instrument.", "et": "Arendada individuaalset meisterlikkust põhipillil."}], "learning_outcomes": [{"en": "Upon completion the course the students:\n* are able to perform the third year mandatory repertoire,\n* are able to apply the techniques taught by the main instrument instructor,\n* are able to independently analyze the transcribed material,\n* prepare two a 20-minute  programs (one solo concert) ;", "et": "* oskab esitada III kursuse kohustuslikku repertuaari,\n* oskab rakendada õppeaasta jooksul omandatud tehnikaid,\n* suudab iseseisvalt analüüsida transkribeeritud materjali,\n* valmistab ette kaks kontsertkava kestusega 20 min (üks neist soolokontsert)"}]}, "_actions": {"is_version_creatable": false, "is_editable": false, "is_deletable": false}}