{"uuid": "f88dec1a-0000-cc54-5677-6fdb17523057", "code": "mt-2012-spring-fulltime-c3", "state": {"code": "confirmed", "et": "Kinnitatud", "en": "confirmed"}, "last_update": "2023-12-21T16:34:08", "title": {"en": "Didactics of Mathematics for Secondary School", "et": "Matemaatika didaktika gümnaasiumile"}, "credits": 3, "credit_type": "ECTS", "target": {"year": {"code": "2012", "et": "2012/2013", "en": "2012/2013"}, "semester": {"code": "spring", "et": "kevad", "en": "spring"}, "study_type": {"code": "fulltime", "et": "päevaõpe", "en": "regular studies"}, "language": {"code": "et", "et": "eesti keel", "en": "Estonian"}, "part": {"code": "0", "et": "Osadeta", "en": "None"}, "faculty": {"code": "MT", "name": {"en": "Faculty of Mathematics and Computer Science", "et": "matemaatika-informaatikateaduskond"}, "email": "math@ut.ee", "phone": "(+372) 737 5860, (+372) 737 5862", "webpage_url": "http://www.math.ut.ee", "address": "J. Liivi 2, 50409,  Tartu, Tartumaa, Eesti", "city": "Tartu", "street": "J. Liivi 2", "zip": "50409", "level": 1, "academic": true, "supports_continuous_learning": true, "is_expired": true}, "course_main_structural_unit": {"code": "LTMS", "name": {"en": "Institute of Mathematics and Statistics", "et": "matemaatika ja statistika instituut"}, "email": "ltms@ut.ee", "phone": "+372 737 5863", "webpage_url": "https://math.ut.ee", "address": "Narva mnt 18\n51009 Tartu linn, \nTartu linn, Tartumaa \nEST", "city": "Tartu linn", "street": "Narva mnt 18", "zip": "51009", "level": 2, "academic": true, "supports_continuous_learning": true, "parent_code": "LT"}, "label": {"en": "12/13 S regular MT", "et": "12/13 K PÕ MT"}}, "general": {"year": {"code": "2012", "et": "2012/2013", "en": "2012/2013"}, "input_languages": [{"code": "et", "et": "eesti keel", "en": "Estonian"}], "structural_unit_shares": [{"structural_unit_code": "LTMS", "structural_unit_name": {"en": "Institute of Mathematics and Statistics", "et": "matemaatika ja statistika instituut"}, "course_share_percent": 100, "coordinating": true}], "type": {"code": "regular", "et": "Tavaline aine", "en": "Regular course"}}, "additional_info": {"is_vota_course": true, "is_continuous_learning_course": false, "study_levels": [{"code": "bachelor", "et": "bakalaureuseõpe", "en": "bachelor's studies"}, {"code": "master", "et": "magistriõpe", "en": "master's studies"}], "hours": {"lecture": 24, "practice": 8, "seminar": 0, "colloquium": 0, "web_learning": 0, "independent_work": 46, "individual_work": 0, "internship": 0}, "is_enlight_course": false}, "overview": {"study_languages": [{"code": "et", "et": "eesti keel", "en": "Estonian"}], "description": {"en": "The different possibilities of treatment of the mathematical topic in grades IV-XII (numbers, algebraic expressions, equations, functions, trigonometry, geometry). The analysis of the mathematics lesson.", "et": "Gümnaasiumi (X-XII kl) põhiteemade käsitlemise metoodika. Matemaatika ainekava koostamine. Matemaatikatunni ettevalmistamine ja tunni analüüs."}, "objectives": [{"en": "The students gain the knowledge and the first skills for the mathematics teaching in grades X-XII.", "et": "Üliõpilane omandab teadmised ja esmased oskused X-XII klassi matemaatika põhiteemade õpetamiseks."}], "learning_outcomes": [{"en": "After passing this course the student", "et": "Selle kursuse läbinud üliõpilane"}, {"en": "1) knows the mental calculating methods and can use them", "et": "1) tunneb peastarvutamise võtteid, oskab neid kasutada"}, {"en": "2) knows the didactics of the number concept expanding, the teaching possibilities of different number sets ", "et": "2) tunneb arvu mõiste laiendamise metoodikat ja erinevate arvuhulkade käsitlemise võimalusi "}, {"en": "3)knows the didactics of percentage teaching", "et": "3) tunneb protsentarvutuse käsitlemise metoodikat"}, {"en": "4) knows the main goals of algebra learning at school and the didactics of algebra", "et": "4) tunneb algebraõpetuse põhieesmärke, algebrateemade käsitlemise metoodikat"}, {"en": "5) knows the didactics of expanding of power concept, can compare different definitions of powers and roots", "et": "5) tunneb astme mõiste laiendamist, oskab võrrelda astmete ja juurte erinevaid definitsioone"}, {"en": "6) knows the didactics of equations and inequalities", "et": "6) tunneb võrrandite ja võrratuste käsitlemise metoodikat"}, {"en": "7) knows the teaching possibilities of elementary functions", "et": "7) tunneb funktsiooni mõiste kujundamise erinevaid teid, elementaarfunktsioonide käsitlemise metoodikat"}, {"en": "8) knows the main goals of the learning of the geometry the teaching of synthetic geometry ", "et": "8) tunneb geomeetriaõpetuse põhieesmärke, sünteetilise geomeetria õpetamist põhikoolis ja gümnaasiumis"}, {"en": "9) knows the didactics of statistics and probability at school", "et": "9) tunneb tõenäosusteooria elementide käsitlemise metoodikat"}, {"en": "10) can complete the syllabus  for the concrete mathematics topic", "et": "10) oskab koostada ainekava iga matemaatikateema osas"}, {"en": "11) can compare different didactical viewpoints about the teaching the same topic", "et": "11) oskab võrrelda erinevaid metoodilisi lähenemisi sama materjali käsitlemiseks"}], "notes": {}}, "grading": {"independent_work": {}, "independent_work_assessments": [{"work_type": {"code": "test", "et": "Kontrolltöö", "en": "test"}, "description": {"et": "Peastarvutamine"}}, {"work_type": {"code": "homework", "et": "Kodutöö", "en": "home work"}, "description": {"et": "Õppematerjali koostamine.\nProtsentülesannete lahendamine. \nTunni analüüs."}}], "grade_preconditions": {}, "grade_evaluation": {"et": "Eksamihinne sisaldab kontrolltöö tulemust ja eksamitöö tulemust."}, "debt_elimination": {}, "assessment_scale": {"code": "grade", "et": "Eristav (A, B, C, D, E, F, mi)", "en": "differentiated (A, B, C, D, E, F, not present)"}, "results_available_from": {}}, "resources": {"web_based": {"code": "3", "et": "lähiõpe", "en": "face-to-face learning"}, "is_moodle_connected": false, "mandatory_materials": "K. Kaasik, L. Lepmann, Väike metoodikaraamat II kooliastme matemaatikaõpetajale, Tln, Avita, 2002."}, "participants": {"lecturers": [{"person_uuid": "06d32fc7-7125-a168-597b-223e2d36bd84", "person_name": "Lea Lepmann", "structural_unit": {"code": "MTMM03", "name": {"en": "Centre of School Mathematics", "et": "koolimatemaatika keskus"}, "level": 3, "academic": false, "supports_continuous_learning": false, "parent_code": "MTMM", "is_expired": true}, "is_responsible": true, "is_teaching": true}]}, "schedule": {"weeks": {"et": "24. - 35. n.  2L n-s, 36.-39. n. 2Sn-s  1 ref => E; "}, "entries": [{"work_type": {"code": "lecture", "et": "loeng", "en": "lecture"}, "topic": {}, "description": {"et": "Peastarvutamise võtted. Peastarvutamise mitmekesistamise teed."}}, {"work_type": {"code": "lecture", "et": "loeng", "en": "lecture"}, "topic": {}, "description": {"et": "Arvu mõiste laiendamine. Naturaalarvud."}}, {"work_type": {"code": "lecture", "et": "loeng", "en": "lecture"}, "topic": {}, "description": {"et": "Murdarvud."}}, {"work_type": {"code": "lecture", "et": "loeng", "en": "lecture"}, "topic": {}, "description": {"et": "Negatiivsed arvud, irratsionaal- ja reaalarvud."}}, {"work_type": {"code": "lecture", "et": "loeng", "en": "lecture"}, "topic": {}, "description": {"et": "Protsentülesannete käsitlemine."}}, {"work_type": {"code": "lecture", "et": "loeng", "en": "lecture"}, "topic": {}, "description": {"et": "Algebraliste avaldiste käsitlemine. Astme mõiste üldistamine. Kontrolltöö."}}, {"work_type": {"code": "lecture", "et": "loeng", "en": "lecture"}, "topic": {}, "description": {"et": "Võrrandite käsitlemine."}}, {"work_type": {"code": "lecture", "et": "loeng", "en": "lecture"}, "topic": {}, "description": {"et": "Tekstülesannete lahendamise metoodika."}}, {"work_type": {"code": "lecture", "et": "loeng", "en": "lecture"}, "topic": {}, "description": {"et": "Võrratuste käsitlemine."}}, {"work_type": {"code": "lecture", "et": "loeng", "en": "lecture"}, "topic": {}, "description": {"et": "Funktsiooni mõiste kujundamine, funktsioonide käsitlemine põhikoolis."}}, {"work_type": {"code": "lecture", "et": "loeng", "en": "lecture"}, "topic": {}, "description": {"et": "Funktsioonide käsitlemine gümnaasiumis."}}, {"work_type": {"code": "lecture", "et": "loeng", "en": "lecture"}, "topic": {}, "description": {"et": "Geomeetriaõpetuse põhijooned. Geomeetria käsitlemine põhikoolis."}}, {"work_type": {"code": "seminar", "et": "seminar", "en": "seminar"}, "topic": {}, "description": {"et": "Tõenäosusteooria ja matemaatilise statistika küsimuste käsitlemine."}}, {"work_type": {"code": "seminar", "et": "seminar", "en": "seminar"}, "topic": {}, "description": {"et": "Koostatud õppematerjalide analüüs."}}, {"work_type": {"code": "seminar", "et": "seminar", "en": "seminar"}, "topic": {}, "description": {"et": "Tutvumine õpetajale vajaliku matemaatikaalase kirjandusega (metoodilised juhendid, töövihikud, kontrolltööde kogumikud, käsiraamatud, ülesannetekogud, lisamaterjalid, jne)."}}, {"work_type": {"code": "seminar", "et": "seminar", "en": "seminar"}, "topic": {}, "description": {"et": "Matemaatikatundide vaatlus videost. Tundide analüüs."}}]}, "registration_info": {"audience": {}, "max_students": 30}, "parent_uuid": "adc191ff-7929-5435-846f-fdd68138761b", "parent_code": "MTMM.00.121", "parent_credits": 3, "_actions": {"is_editable": false, "is_moodle_editable": false, "is_deletable": false}}