{"uuid": "45f1dd3c-ab34-a347-57bb-b6b019c3c5de", "code": "SVPC.01.033", "state": {"code": "confirmed", "et": "Kinnitatud", "en": "confirmed"}, "last_update": "2024-12-17T14:31:23", "title": {"en": "Organizational Branding", "et": "Organisatsiooni brändi arendamine"}, "credits": 8, "general": {"input_languages": [{"code": "et", "et": "eesti keel", "en": "Estonian"}], "structural_unit_shares": [{"structural_unit_code": "SVPC01", "structural_unit_name": {"en": "Department of Entrepreneurship", "et": "ettevõtlusosakond"}, "course_share_percent": 100, "coordinating": true}], "type": {"code": "regular", "et": "Tavaline aine", "en": "Regular course"}, "structural_units": [{"code": "SVPC01", "name": {"en": "Department of Entrepreneurship", "et": "ettevõtlusosakond"}, "phone": "+372 445 0532", "address": "Ringi 35\n80012 Pärnu linn, \nPärnu linn, Pärnumaa \nEST", "city": "Pärnu linn", "street": "Ringi 35", "zip": "80012", "level": 3, "academic": true, "supports_continuous_learning": false, "parent_code": "SVPC"}]}, "additional_info": {"duration_in_semesters": 2, "occurrence_frequency": {"code": "semester", "et": "igal semestril", "en": "every semester"}, "assessment_scale": {"code": "pass", "et": "Eristamata (arv, m.arv, mi)", "en": "non-differentiated (pass, fail, not present)"}, "is_vota_course": false, "is_continuous_learning_course": true}, "overview": {"description": {"en": "Design thinking. Brand. Brand management. Brand development. Rebranding.", "et": "Disainmõtlemine. Bränd. Brändi juhtimine. Brändi arendamine. Rebrändimine."}, "objectives": [{"en": "The aim of the course is to develop the ability to cooperate within the framework of development projects by combining design thinking and brand knowledge into an integral whole through brand management and development.", "et": "Aine eesmärk on arendada koostöö tegemise oskust arendusprojektide raames sidudes disainmõtlemise ja brändialaseid teadmisi tervikuks läbi brändi juhtimise ja arendamise."}], "learning_outcomes": [{"en": "Upon the completion of the course the student:", "et": "Õppeaine läbinud õppija: "}, {"en": "1) knows the basics of brand creation;", "et": "1) teab brändi loomise aluseid;"}, {"en": "2) is able to develop a brand as part of teamwork;", "et": "2) oskab meeskonnas töötades arendada brändi; "}, {"en": "3) is able to combine design thinking and branding knowledge for solving economic problems.", "et": "3) oskab ühendada disainmõtlemise ja brändialaseid teadmised majandusprobleemi lahendamisel."}]}, "_actions": {"is_version_creatable": false, "is_editable": false, "is_deletable": false}}