{"KURSUSE_NIMI": "Suguteedeinfektsioonide mikrobioloogia", "KURSUSE_KOOD": "ARMB.01.041", "EAP": 2, "KURSUSE_TYYP": "Tavaline aine", "KURSUSE_KEELED": ["eesti keel"], "VOTA": true, "SEMESTER": "kevad", "OPPETYYP": "päevaõpe", "TUNDIDE_JAOTUS": {"lecture": 12, "practice": 0, "seminar": 0, "colloquium": 0, "web_learning": 0, "independent_work": 40, "individual_work": 0, "internship": 0}, "HINDAMISSKAALA": "pass", "KIRJELDUS": "Suguteede mikrofloora. Tupe infektsioonid. Emakakaela infektsioonid. Ülemiste naissuguteede infektsioonid. Välisgenitaalide infektsioonid. Meessuguteede infektsioonidObjectives/eesmärkid:  Kursuse eesmärk on tutvustada olulisemate suguteedeinfektsioonide tekitajaid ja mikrobioloogilise diagnoosimise võimalusi.Learning outcomes/õpiväljund:  Kursuse läbimise tulemusena üliõpilane: 1) tunneb normaalse suguteede mikrobioota kujunemist ja koostist; 2) mõistab suguteede mikrobiootat mõjutavad faktoreid; 3) teab olulisemate mees- ja naissuguteedeinfektsioonide tekitajaid ning tunneb vastavate haiguste patogeneesi; 4) oskab valida optimaalseid meetodeid levinumate suguteedeinfektsioonide diagnoosimisesks; 5) teab suguteedeinfektsioonide ravi printsiipe. Vajalik info on olemas Moodle'i kursusel."}