{"KURSUSE_NIMI": "Frege loengud", "KURSUSE_KOOD": "FLFI.04.101", "EAP": 3, "KURSUSE_TYYP": "Tavaline aine", "KURSUSE_KEELED": ["eesti keel"], "VOTA": true, "KOHUSTUSLIKUD_EELDUSAINED": [], "SOOVITUSLIKUD_EELDUSAINED": ["Sissejuhatus filosoofiasse"], "SEMESTER": "sügis", "OPPETYYP": "päevaõpe", "TUNDIDE_JAOTUS": {"lecture": 12, "practice": 0, "seminar": 16, "colloquium": 0, "web_learning": 0, "independent_work": 50, "individual_work": 0, "internship": 0}, "HINDAMISSKAALA": "pass", "KIRJELDUS": "Gottlob Frege nimeliste teoreetilise filosoofia loengute ettevalmistuseks peetakse seminare, kus käsitletakse lektori teemakohaseid tekste. Vajalik on osalemine ettevalmistavatel seminaridel, Frege loengutel ja loengutega seotud töötoas (juhul kui see antud aastal toimub).Objectives/eesmärkid:  Aine eesmärk on valmistada üliõpilasi ette osalemiseks iga-aastastel Frege loengutel, mida peab rahvusvaheliselt tunnustatud külaline, võimaldada neil mõista Frege loengute ja loengutele järgneva töötoa teemasid ning õpitu üle reflekteerida.Learning outcomes/õpiväljund:  Õppeaine läbinud üliõpilane saab aru Frege loengute sisust, oskab loengute teemadel kaasa mõtelda ning õpitu üle reflekteerida."}