{"KURSUSE_NIMI": "Gilles Deleuze 100", "KURSUSE_KOOD": "FLFI.01.129", "EAP": 3, "KURSUSE_TYYP": "Tavaline aine", "KURSUSE_KEELED": ["eesti keel"], "VOTA": true, "SEMESTER": "kevad", "OPPETYYP": "päevaõpe", "TUNDIDE_JAOTUS": {"lecture": 22, "practice": 0, "seminar": 6, "colloquium": 0, "web_learning": 0, "independent_work": 50, "individual_work": 0, "internship": 0}, "HINDAMISSKAALA": "pass", "KIRJELDUS": "Aine annab ülevaate Gilles Deleuze'i filosoofiast. Käsitletakse tema põhimõisteid (erinevus, paljusus, immanentsusväli, virtuaalsus ja aktuaalsus, organiteta keha ja ihamasinad, risoom, seade jne), vaadeldakse tema kriitikat lääne esindusmõtlemise ehk dogmaatilise mõttepildi aadressil, uuritakse tema tõlgendavat suhet filosoofa ajalooga (Spinoza, Hume, Kant, Nietzsche, Bergson) ja ühisloomet oma kaasaegsetega (Foucault, Guattari, Lacan) ning arutatakse tema mõttekäikude relevantsust tänapäeva maailma arengute kontekstis (protsessiontoloogia, voolav modernsus, toimijavõrgustikud, afektiivne pööre).Objectives/eesmärkid:  Tutvustada humanitaarias äärmiselt mõjukat filosoofi; selgitada tema väga uudsete mõistete \"tööriistakasti\", mille abil mõtestada ennast, maailma ja kõike seal toimuvat; arendada dünaamilist, paindlikku ja protsessipõhist mõtlemist.Learning outcomes/õpiväljund:  Aine läbinud üliõpilane: i) orienteerub mõnevõrra Deleuze'i filosoofias, ii) omandab kriitilised kontseptuaalsed vahendid ühiskondlike ja kultuurinähtuste analüüsiks, iii) hakkab loodetavasti praktiseerima mõtlemise loovat perspektiivi, mille suunisteks on paljusus, erinevus, uudsus ja intensiivsus."}