{"KURSUSE_NIMI": "Teoloogia süsteem", "KURSUSE_KOOD": "HVUS.02.004", "EAP": 3, "KURSUSE_TYYP": "Tavaline aine", "KURSUSE_KEELED": ["eesti keel"], "VOTA": true, "SEMESTER": "kevad", "OPPETYYP": "päevaõpe", "TUNDIDE_JAOTUS": {"lecture": 8, "practice": 0, "seminar": 18, "colloquium": 0, "web_learning": 0, "independent_work": 52, "individual_work": 0, "internship": 0}, "HINDAMISSKAALA": "grade", "KIRJELDUS": "Tutvumine kristliku mõtlemise sisu, meetodite ja allikatega süstemaatilise teoloogia raames.Objectives/eesmärkid:  Orienteerumine süstemaatilise teoloogia põhilistes küsimustes.Learning outcomes/õpiväljund:  Üliõpilane tunneb peamisi normatiivseid väiteid, mis on esitatud usutunnistustes; oskab näha nende väidete seost nende esitamise ajastuga; seostab neid kriitiliselt ja loovalt tänapäevaste teadmistega interdistsiplinaarselt; oskab demonstreerida nende väidete rolli kiriku(te)s, akadeemias, ühiskonnas laiemalt. Õppetöö toimub kas auditoorselt või moodle's, vastavalt olukorrale"}