{"KURSUSE_NIMI": "Omakultuur", "KURSUSE_KOOD": "HVVK.12.001", "EAP": 3, "KURSUSE_TYYP": "Tavaline aine", "KURSUSE_KEELED": ["eesti keel"], "VOTA": true, "SEMESTER": "kevad", "OPPETYYP": "päevaõpe", "TUNDIDE_JAOTUS": {"lecture": 32, "practice": 0, "seminar": 0, "colloquium": 0, "web_learning": 0, "independent_work": 46, "individual_work": 0, "internship": 0}, "HINDAMISSKAALA": "grade", "KIRJELDUS": "Talletatud pärimuslikku arhiivimaterjali interpreteerides ning sellealaseid teaduslikke seisukohti taustaks võttes avatakse iseseisva töö ja seminaride käigus eestlaste maailmavaadet, identiteediloomet ja selle muutumist diakroonilises plaanis.Objectives/eesmärkid:  Tutvustada eestlaste maailmapildi kujunemist pärimuskultuuriliste allikate põhjal.\nAidata aru saada omakultuuri ja enesemääratluse nähtustest.Learning outcomes/õpiväljund:  Üliõpilane: - orienteerub eesti pärimuskultuuri kujunemisloos; - tunneb ja mõistab eesti kultuuriloo protsessi kui sidusat tervikut pärimuslikust maailmapildist tänapäeva; - tunneb folkloori uurimise teaduslikku traditsiooni Eestis ja oskab huvi korral sellega edasi töötada; - tunneb eesti traditsioonilist usundit; - tunneb pärimuslikku kalendrit; - tunneb ja oskab eristada suulise pärimuse eri vorme; - mõistab identiteediloome ja  folklooriprotsessi spetsiifikat. Suhestub eesti kultuurilooga, VKA omakultuuri teesidega  ja suudab seda kasutada hilisemas loometegevuses."}