{"KURSUSE_NIMI": "Etnograafiline ehe II", "KURSUSE_KOOD": "HVVK.01.129", "EAP": 3, "KURSUSE_TYYP": "Tavaline aine", "KURSUSE_KEELED": ["eesti keel"], "VOTA": true, "HINDAMISSKAALA": "grade", "KIRJELDUS": "Antakse ülevaade 18.-19. sajandi kuhiksõlgedest, erinevate piirkondade eripäradest, kuhiksõlgede erinevatest suurustest ja tüüpidest, dekoorimise võtetest (graveerimine, joondekoor). Õpetatakse kuhiksõlgede valmistamist.Objectives/eesmärkid:  Erinevate kuhiksõlgede valmistamise võtete tutvustamineLearning outcomes/õpiväljund:  Aine edukal läbimisel üliõpilane omab ülevaadet erinevatest kuhiksõle tüüpidest; oskab kasutada kuhiksõle valmistamise võtteid; oskab valmistada kuhiksõlge."}