{"KURSUSE_NIMI": "Hägus loogika ja ligikaudsed arvutusmeetodid", "KURSUSE_KOOD": "LTAT.02.005", "EAP": 6, "KURSUSE_TYYP": "Tavaline aine", "KURSUSE_KEELED": ["eesti keel"], "VOTA": true, "SEMESTER": "kevad", "OPPETYYP": "päevaõpe", "TUNDIDE_JAOTUS": {"lecture": 32, "practice": 32, "seminar": 0, "colloquium": 0, "web_learning": 0, "independent_work": 92, "individual_work": 0, "internship": 0}, "HINDAMISSKAALA": "pass", "KIRJELDUS": "Hägus loogika on kujunenud tõhusaks vahendiks probleemide lahendamisel erinevates valdkondades. Selle sünergiline kasutamine koos neuroarvutustega ja evolutsiooniliste tehnikatega võimaldab luua töökindlaid intelligentseid süsteeme. Sellist erinevate meetodite kombinatsiooni tuntakse ka kui ligikaudseid arvutusmeetodeid. Käesolev kursus tutvustab erinevaid ligikaudsete arvutusmeetodeid nt nn klassikalised hägusloogika süsteemid, hägusad neurosüsteemid, granulaarne arvutamine. Granulaarne arvutamine on uus neuroarvutuste paradigma, mis võimaldab luua täpsemaid ja\nparemini tõlgendatavaid mudeleid. Kursuse käigus võrreldakse ka üksikute ja kombineeritud tehnikate\nkasutamise tulemusi praktilistes olukordades.Objectives/eesmärkid:  Tutvustada tudengitele peamiseid teemasi ja arenguid hägusa loogika ja ligikaudse arvutusmeetodite valkdonnas (nt neuro-hägusad süsteemid, evolutsioonilised tehnikad, granulaarne arvutamine)\nÕpetada tudengitele ligikaudsete arvutusmeetodite eesmärke ja tehnikaid Õpetada tudengitele nende tehnikate kasutamist erinevate tüüpprobleemide lahendamisel.Learning outcomes/õpiväljund:  Kursuse läbinud üliõpilane: -Oskab kirjeldada ja argumenteerida hajusa loogika ja ligikaudsete arvutusmeetodite teemadel; -Oskab kasutada vähemalt kahte ligikaudse arvutuse meetodit; -Oskab valida ja rakendada sobivat ligikaudse arvutamise meetodit probleemi lahendamiseks. e-learning in Zoom, Moodle."}