{"KURSUSE_NIMI": "Bioressursside tehnoloogiad ja bioenergeetika", "KURSUSE_KOOD": "LTKT.04.007", "EAP": 3, "KURSUSE_TYYP": "Tavaline aine", "KURSUSE_KEELED": ["eesti keel"], "VOTA": true, "SEMESTER": "sügis", "OPPETYYP": "päevaõpe", "TUNDIDE_JAOTUS": {"lecture": 12, "practice": 0, "seminar": 12, "colloquium": 0, "web_learning": 0, "independent_work": 54, "individual_work": 0, "internship": 0}, "HINDAMISSKAALA": "grade", "KIRJELDUS": "Kursuses käsitletakse süvendatult biojäätmete käitluse tehnoloogiaid ning võimalusi biojäätmete kasutamiseks energeetilisel otstarbel. Biojäätmete ohutu käitlemine on säästva arengu printsiipide üks olulisemaid valdkondi, mille kaudu tagatakse jätkusuutlike tehnoloogiate rakendumine jäätmekäitluses.Objectives/eesmärkid:  Kursuse eesmärk on õppida tundma biojäätmete käitluse ja bioressursside töötlemise tehnoloogiaid nii nende kasutamisel energia tootmiseks kui ka väärindamisel materjalide tootmisel.Learning outcomes/õpiväljund:  Õppeaine läbinu: - omab ülevaadet bioressurssidest nii Eesti, Euroopa Liidu kui ka gloobaalsel tasandil; - teab biojäätmete klassifitseerimise aluseid ja jäätmekäitluse keskkonnahoidlikke meetodeid  - tunneb biojäätmete käitlustehnoloogiaid ja neid iseloomustavaid näitajaid - analüüsib biojäätmete kasutuspotentsiaali ja tehnoloogiliste meetodite efektiivsust; - teab peamisi biojäätmete energiakasutuse võimalusi."}