{"KURSUSE_NIMI": "Andmeanalüüsi lühikursus R keeles", "KURSUSE_KOOD": "MVPT.00.009", "EAP": 1, "KURSUSE_TYYP": "Tavaline aine", "KURSUSE_KEELED": ["eesti keel"], "VOTA": true, "HINDAMISSKAALA": "pass", "KIRJELDUS": "Andmeanalüüsi põhiliste töövõtete ja rutiinide omandamine R keeles.Objectives/eesmärkid:  Eesmärk on anda baasoskused R-i kasutamiseks tidyverse keskkonnas, mis võimaldab tudengitel jätkata iseseisvalt R-i kasutamisega vastavalt oma vajadustele. See on soovituslik eeldusaine kursusele \"Kaks semestrit teadlase kingades: uurimisküsimusest publikatsioonini\", mis on ehitatud vastama selle kursuse vajadustele.Learning outcomes/õpiväljund:  Üliõpilane oskab koostada andmeanalüüsi töövoogu dokumenteeriva R Notebook dokumendi, mis hõlmab andmete sisselugemist R-i töökeskkonda ühes põhiliste andmemanipulatsioonide ja andmete visualiseerimisega."}