{"KURSUSE_NIMI": "Pärimisõigus", "KURSUSE_KOOD": "P2OG.01.027", "EAP": 3, "KURSUSE_TYYP": "Tavaline aine", "KURSUSE_KEELED": ["eesti keel"], "VOTA": true, "KOHUSTUSLIKUD_EELDUSAINED": ["Tsiviilõiguse üldosa", "Võlaõiguse üldosa", "Asjaõigus"], "SOOVITUSLIKUD_EELDUSAINED": [], "SEMESTER": "kevad", "OPPETYYP": "sessioonõpe", "TUNDIDE_JAOTUS": {"lecture": 22, "practice": 0, "seminar": 0, "colloquium": 0, "web_learning": 0, "independent_work": 56, "individual_work": 0, "internship": 0}, "HINDAMISSKAALA": "grade", "KIRJELDUS": "Kursuse raames käsitletakse pärimisõiguse põhimõtteid ja peamisi mõisteid; seadus-, testamendi- ja pärimislepingujärgset pärimist Eestis ning võrreldakse neid teiste Euroopa maade vastavate pärimisõiguse instituutidega.Samuti leiab käsitlemist pärimise käik ja pärimisõigusega seonduv notari- ning kohtupraktikaObjectives/eesmärkid:  Õppeaine eesmärgiks on anda üliõpilastele teadmised pärimisõiguse teooriast ja kohaldamise praktikast, oskused lahendada pärimisõiguse alaseid vaidlusi ja nõustada pärimisega seonduvaid toimingutes.Learning outcomes/õpiväljund:  Õppeaine läbinud õppija: Aine läbinud üliõpilane:\n*\tteab pärimisõiguse põhimõtteid; \n*\ttunneb pärimisõiguse põhilisi mõisteid;\n*\tmõistab ja oskab selgitada pärimisõiguse instituutide olemust;\n*\ttunneb pärimismenetluse etappe;\n*\ttunneb olulisemaid pärimisega seonduvaid nõudeid;\n*\tmõistab ja oskab selgitada pärimisõiguse seoseid teiste õigusharudega;\n*\ttunneb ja oskab kasutada pärimisõiguse valdkonna kirjandust ja kohtupraktikat;\n*      oskab analüüsida pärimisõiguslikke probleeme ja pakkuda lahendusi;\n*      omab ülevaadet pärimisõiguse reguleerimise põhimõtetest rahvusvahelisel ja Euroopa Liidu tasemel;\n*      oskab planeerida rühmatööd ja töötada tõhusalt grupis õigusliku probleemi lahendamisel\n\nÕppetöö toimub loengute ja seminaride vormis. \nÜliõpilane omandab pärimisõiguslike kaasuste lahendamise metoodika ja saab vajaliku oskuse kaasuste lahendamiseks nii pärimisseaduse kui teiste asjassepuutuvate õigusnormide alusel."}