{"KURSUSE_NIMI": "Kontserdi helindamine", "KURSUSE_KOOD": "P2VK.02.629", "EAP": 3, "KURSUSE_TYYP": "Tavaline aine", "KURSUSE_KEELED": ["eesti keel"], "VOTA": true, "KOHUSTUSLIKUD_EELDUSAINED": ["Muusikatehnoloogia alused"], "SOOVITUSLIKUD_EELDUSAINED": [], "SEMESTER": "kevad", "OPPETYYP": "päevaõpe", "TUNDIDE_JAOTUS": {"lecture": 0, "practice": 24, "seminar": 0, "colloquium": 0, "web_learning": 0, "independent_work": 54, "individual_work": 0, "internship": 0}, "HINDAMISSKAALA": "pass", "KIRJELDUS": "Tutvustab ja õpetab kasutama kaasaegseid kontsertide helindamise vahendeid nagu erinevad mikserpuldid ja võimendussüsteemid.Objectives/eesmärkid:  Õppeaine eesmärgiks on:  õpetada kasutama tänapäevast ürituste helindamise tehnikat ning võimaldada jälgida juhendaja tööd ning osaleda praktikabaasi tööprotsessides läbi reaalsete situatsioonide. Eesmärgiks on pakkuda võimalust omandada oskused töötamisel ja suhtlemisel kollektiivi või artistidega ning kaasaegse helitehnikaga.Learning outcomes/õpiväljund:  Aine läbinud üliõpilane:\n*\tmõistab helindamiseks vajalike seadmete ühenduste ja ühildamise üldstruktuuri ning plokkskeemi;\n*\t mõistab ja selgitab helindamisel kasutatava aparatuuri tööpõhimõtteid;\n*\t mõistab ja tunneb peamisi helindamisel kasutatavaid analoog- ja digitaalseid mikserpulte;\n*\t oskab vastavalt ürituse asukohale ja esinejate arvule ning iseärasustele planeerida vajaliku suuruse ja võimsusega helitehnika ja kaasnevad seadmed; \n*\tsuudab iseseisvalt planeerida ja helindada TÜ VKA muusikaosakonna kontserte."}