{"KURSUSE_NIMI": "Kiirlugemine", "KURSUSE_KOOD": "SHHI.01.077", "EAP": 2, "KURSUSE_TYYP": "Tavaline aine", "KURSUSE_KEELED": ["eesti keel"], "VOTA": true, "HINDAMISSKAALA": "pass", "KIRJELDUS": "Olulisemateks teemadeks on aeglase lugemise põhjused, teksti sisu mõistmise viisid, kiirlugemise harjutamise võtted ja vaimse töö efektiivsuse tõstmise võimalused.\nKursus toimub e-õppena, mille käigus üliõpilased kiirlugemistarkvara 5.1.30 abil: \n1.\tTeevad lugemiskiiruse ja omandamiskiiruse teste\n2.\tHarjutavad kiirlugemise võtteid\na)\ttagasivaatamiste vältimine,\nb)\tnägemisvälja suurendamine,\nc)\tlugemine sõnarühmade kaupa.\nTarkvara salvestab kõikide õppijate kõikide testide ja harjutuste tulemused ja võimaldab õppijal jälgida oma lugemisoskuse arengut.Objectives/eesmärkid:  Kiirlugemiskursuse eesmärgiks on tutvustada teksti sisu täielikuma mõistmise ning kiirema omandamise võtteid ja harjutada nende kasutamist kiirlugemise tarkvaraga.Learning outcomes/õpiväljund:  Õppeaine läbinud üliõpilane 1) teab, millised on aeglase lugemise põhjused, 2) teab, milliste võtete abil saab teksti sisu paremini mõista ja kiiremini omandada, 3) on arendanud oskusi teksti sisu kiiremaks ja täielikumaks omandamiseks."}