{"KURSUSE_NIMI": "Õppimine, õpetamine ja juhendamine", "KURSUSE_KOOD": "SVHI.01.070", "EAP": 6, "KURSUSE_TYYP": "Tavaline aine", "KURSUSE_KEELED": ["eesti keel"], "VOTA": true, "HINDAMISSKAALA": "pass", "KIRJELDUS": "Kursuse käigus käsitletakse järgmisi teemasid: õppimise ja õpetamise olemus; enesejuhitavus õppimises; õppeprotsessi etapid; ainekursuse kavandamine; õppimist toetav hindamine; erinevad õppemeetodid ja nende valiku põhimõtted; keeruliste teemade käsitlemine; konstruktiivse tagasiside andmine; juhendaja rollid ja ülesanded; õpetamise ja teadustöö eetika.Objectives/eesmärkid:  Ainekursuse eesmärk on laiendada doktorantide teadmisi ja oskusi õppida ja õpetada erinevates õpikeskkondades (sealhulgas ülikoolis, e-õppes, täiskasvanuhariduses). \nKursusel keskendutakse õppimise, õpetamise ja juhendamise kavandamisele ja kogemuste reflekteerimisele.Learning outcomes/õpiväljund:  Kursuse lõpuks doktorandid: 1.\tmärkavad oma õppimisvajadusi ning juhivad teadlikult enda õppimist erinevates õpikeskkondades; 2.\tmõtestavad õppimise, õpetamise ja juhendamise olemust ülikoolis ning rakendavad õppimis- ja õpetamisteooriaid üliõpilaste õppimise toetamiseks erinevates õpikeskkondades (sealhulgas e-õppes) 3.\tkavandavad ainekursust kui tervikut ja õppimist toetavat hindamist ning annavad õppimist toetavat tagasisidet (sealhulgas arvestavad e-õppe ja kontaktõppe sidusust); 4.\tvalivad teadlikult õpiväljundite saavutamiseks sobivaid õppemeetodeid ja rakendavad neid praktikas; 5.\tkavandavad juhendamisprotsessi ning teadvustavad juhendaja ja juhendatava rolle ning ülesandeid juhendamisprotsessis; 6.\ton reflekteerinud oma õpetamise üle ning on valmis jätkama õppejõu tegevuseks vajalikku asjatundlikkuse arendamist."}