{"KURSUSE_NIMI": "Rahanduse alused", "KURSUSE_KOOD": "SVNC.00.020", "EAP": 3, "KURSUSE_TYYP": "Tavaline aine", "KURSUSE_KEELED": ["eesti keel"], "VOTA": true, "SEMESTER": "sügis", "OPPETYYP": "sessioonõpe", "TUNDIDE_JAOTUS": {"lecture": 10, "practice": 6, "seminar": 0, "colloquium": 0, "web_learning": 0, "independent_work": 62, "individual_work": 0, "internship": 0}, "HINDAMISSKAALA": "grade", "KIRJELDUS": "Rahanduse aine ja finantskeskkond. Eraisiku rahanduse alused. Raha ajaväärtus. Väärtpaberite analüüs. Pangateenused. Investeerimise protsess ja strateegiad. Fondi- ja börsiinvesteeringud.Objectives/eesmärkid:  Õpetusega taotletakse, et õppija omandab rahanduse alased põhiteadmised ja -sõnavara, õpib tundma rahanduse spetsiifikat, omandab väärtuspõhise mõttelaadi ning arendab rahandustööks vajalikke praktilisi oskusi, analüüsivõimet ja probleemide lahendamise oskusi nii enda rikkuse suurendamiseks kui ka tegelemiseks ettevõtlusesLearning outcomes/õpiväljund:  Kursuse läbinud üliõpilane teab:\n* eraisiku (isikliku)rahanduse põhikontseptsioone, sh. raha ajaväärtuse kontseptsioone\n* finantsmatemaatika põhikontseptsioone\n* väärtpaberite liike ja ettevõtte finantseerimise võimalusi\n* kommertspanganduse terminoloogiat ja pakutavaid teenuseid\n* investeerimispanganduse terminoloogiat ja pakutavaid teenuseid\n* Eesti finantskeskkonda (sh finantsturud)\nKursuse läbimisel õppija oskab:\n* oma elus teha põhjendatud rahandusotsuseid\n* teha lihtsamaid finantsmatemaatilisi arvutusi taskuarvuti ja MS Exceli abil\n* arvutada väärtpaberite väärtust, tulusust, hinda, riski\n* koostada ja analüüsida pangalaenu ja liisingu graafikut, teha valuutaarvutusi ja hinnata krediidikulukuse määra finantseerimisel\n* hinnata finantsinvesteeringute tulu, kulu, kasumit ja kasumlikkust ning ka makse. Uued õppejuhised ja teated edastatakse üliõpilastele Moodle`i vahendusel ning vajadusel otse e-posti aadressile."}