{"KURSUSE_NIMI": "Info ja infotöö karjäärinõustamises", "KURSUSE_KOOD": "SVPH.00.024", "EAP": 6, "KURSUSE_TYYP": "Tavaline aine", "KURSUSE_KEELED": ["eesti keel"], "VOTA": true, "SEMESTER": "kevad", "OPPETYYP": "päevaõpe", "TUNDIDE_JAOTUS": {"lecture": 20, "practice": 8, "seminar": 4, "colloquium": 0, "web_learning": 0, "independent_work": 124, "individual_work": 0, "internship": 0}, "HINDAMISSKAALA": "pass", "KIRJELDUS": "Kursuses käsitletakse järgmisi teemasid:\nInfoteaduse põhimõisted ja peamised karjääriteooriad, mis on seotud karjääriinfoga.\nIndividuaalne karjääriinfo vahendamine, aluseks J. Sampson`i teooria.\t\nKliendi juhendamine tööotsimis- ja haridusvalikute tegemise oskuste ning infopädevuse arendamisel.\nKarjääriinfo haldamine ja edastamine.\nÜlevaade haridussüsteemsit, tööturust ja palgainfost. \nSuhtlemine meediagaObjectives/eesmärkid:  Suurendada teadmisi kliendi vajadustele tuginevast karjääriinfo vahendamise protsessist ja parandada  sellealaseid praktilisi oskuseid, ennekõike teemade haridussüsteem, tööturg, palgainfo ja meedia käsitlemise kaudu.Learning outcomes/õpiväljund:  Kursuse läbinu - teab infoteaduse põhimõisted ja peamisi karjääriteooriad, mis on seotud karjääriinfoga. - teab J. Sampson`i teooriale tugineva individuaalse karjääriinfo vahendamise põhimõtteid. - oskab juhendada klienti tööotsimis- ja haridusvalikute tegemise oskuste ning infopädevuse arendamisel. - teab, kuidas otsida infot järgmiste teemade kohta: haridussüsteem, tööturg ja palgainfo.  - teab esmaseid võtteid meediaga suhtlemisel."}